ssxtd/__init__.py
ssxtd/parsers.py
ssxtd/semi_structured_xml_to_dict.py
ssxtd-1.1.0.dist-info/LICENSE
ssxtd-1.1.0.dist-info/METADATA
ssxtd-1.1.0.dist-info/WHEEL
ssxtd-1.1.0.dist-info/top_level.txt
ssxtd-1.1.0.dist-info/RECORD
