Metadata-Version: 2.1
Name: ssxtd
Version: 1.1.0
Summary: semi structured xml to dict
Home-page: https://github.com/xgodon/ssxtd
Author: Xavier Godon
Author-email: xavier.godon@protonmail.com
License: MIT
Platform: UNKNOWN
Classifier: Programming Language :: Python :: 3
Classifier: License :: OSI Approved :: MIT License
Classifier: Operating System :: OS Independent
Requires-Dist: bs4
Requires-Dist: tqdm
